distance_metrics/__init__.py
distance_metrics/lcs.py
distance_metrics-0.0.2.dist-info/METADATA
distance_metrics-0.0.2.dist-info/RECORD
distance_metrics-0.0.2.dist-info/WHEEL
distance_metrics-0.0.2.dist-info/top_level.txt
metrics/__init__.py
metrics/lcs.py
