Metadata-Version: 2.1
Name: distance-metrics
Version: 0.0.2
Summary: Python module of less-common metrics.
Home-page: https://github.com/Thijsvanede/metrics
Author: Thijs van Ede
Author-email: t.s.vanede@utwente.nl
License: UNKNOWN
Platform: UNKNOWN
Classifier: Programming Language :: Python :: 3
Classifier: License :: OSI Approved :: MIT License
Classifier: Operating System :: OS Independent
